justone.py
justone-0.2.0.dist-info/License
justone-0.2.0.dist-info/METADATA
justone-0.2.0.dist-info/WHEEL
justone-0.2.0.dist-info/entry_points.txt
justone-0.2.0.dist-info/top_level.txt
justone-0.2.0.dist-info/RECORD
